hello_module/__init__.py
hello_module/hello.py
hello_module/test_hello.py
hello_module/test_utils.py
hello_module/utils.py
hello_python_cli-0.0.9.data/scripts/hello
hello_python_cli-0.0.9.dist-info/METADATA
hello_python_cli-0.0.9.dist-info/WHEEL
hello_python_cli-0.0.9.dist-info/top_level.txt
hello_python_cli-0.0.9.dist-info/RECORD
