Metadata-Version: 2.1
Name: hello-python-cli
Version: 0.0.9
Summary: Simple python hello cli program
Home-page: UNKNOWN
Author: Mike Kinney
Author-email: mike.kinney@gmail.com
License: UNKNOWN
Platform: UNKNOWN
